odoo/addons/stock_exception/README.rst
odoo/addons/stock_exception/__init__.py
odoo/addons/stock_exception/__manifest__.py
odoo/addons/stock_exception/data/stock_exception_data.xml
odoo/addons/stock_exception/i18n/stock_exception.pot
odoo/addons/stock_exception/models/__init__.py
odoo/addons/stock_exception/models/exception_rule.py
odoo/addons/stock_exception/models/stock.py
odoo/addons/stock_exception/models/stock_move.py
odoo/addons/stock_exception/readme/CONTRIBUTORS.rst
odoo/addons/stock_exception/readme/DESCRIPTION.rst
odoo/addons/stock_exception/security/ir.model.access.csv
odoo/addons/stock_exception/static/description/icon.png
odoo/addons/stock_exception/static/description/index.html
odoo/addons/stock_exception/views/stock_view.xml
odoo/addons/stock_exception/wizard/__init__.py
odoo/addons/stock_exception/wizard/stock_exception_confirm.py
odoo/addons/stock_exception/wizard/stock_exception_confirm_view.xml
odoo14_addon_stock_exception-14.0.1.0.2.dist-info/METADATA
odoo14_addon_stock_exception-14.0.1.0.2.dist-info/WHEEL
odoo14_addon_stock_exception-14.0.1.0.2.dist-info/top_level.txt
odoo14_addon_stock_exception-14.0.1.0.2.dist-info/RECORD
